{
  "stats": {
    "total_voters": 7727638,
    "by_party": {
      "UNA": 3038392,
      "REP": 2324240,
      "DEM": 2314183,
      "LIB": 46324,
      "GRE": 4499
    },
    "by_race": {
      "W": 4920739,
      "B": 1492676,
      "U": 732664,
      "O": 347219,
      "A": 142476,
      "I": 55265,
      "M": 35480,
      "P": 1118,
      " ": 1
    },
    "by_gender": {
      "F": 3803413,
      "M": 3244184,
      "U": 680030,
      " ": 11
    },
    "by_age_group": {
      "18-25": 929352,
      "26-35": 1300464,
      "36-50": 1749444,
      "51-65": 1814750,
      "65+": 1933628
    },
    "by_county": {
      "WAKE": 850715,
      "MECKLENBURG": 826050,
      "GUILFORD": 388940,
      "FORSYTH": 271252,
      "DURHAM": 245418,
      "CUMBERLAND": 220491,
      "BUNCOMBE": 214861,
      "NEW HANOVER": 186416,
      "UNION": 183154,
      "JOHNSTON": 169063,
      "GASTON": 162764,
      "CABARRUS": 161891,
      "IREDELL": 148684,
      "BRUNSWICK": 144928,
      "ONSLOW": 131197,
      "PITT": 124910,
      "DAVIDSON": 122483,
      "ALAMANCE": 119625,
      "CATAWBA": 117977,
      "ORANGE": 111823,
      "ROWAN": 101127,
      "RANDOLPH": 99064,
      "HARNETT": 94815,
      "HENDERSON": 91676,
      "MOORE": 80796,
      "CRAVEN": 76713,
      "WAYNE": 76646,
      "ROBESON": 76358,
      "NASH": 70791,
      "LINCOLN": 70417,
      "CLEVELAND": 69374,
      "CHATHAM": 64053,
      "ROCKINGHAM": 63978,
      "BURKE": 60485,
      "CARTERET": 57526,
      "FRANKLIN": 56403,
      "CALDWELL": 55629,
      "WILSON": 54387,
      "PENDER": 53330,
      "SURRY": 48753,
      "HAYWOOD": 48110,
      "RUTHERFORD": 47148,
      "STANLY": 46953,
      "WILKES": 45330,
      "WATAUGA": 44304,
      "GRANVILLE": 41800,
      "LEE": 41348,
      "SAMPSON": 38453,
      "LENOIR": 37656,
      "COLUMBUS": 37153,
      "HOKE": 36384,
      "EDGECOMBE": 35334,
      "HALIFAX": 34314,
      "STOKES": 33761,
      "BEAUFORT": 33747,
      "DAVIE": 33642,
      "DARE": 32588,
      "DUPLIN": 32068,
      "MCDOWELL": 31040,
      "JACKSON": 30726,
      "PASQUOTANK": 30598,
      "MACON": 29380,
      "RICHMOND": 28438,
      "PERSON": 28227,
      "VANCE": 28034,
      "TRANSYLVANIA": 26659,
      "ALEXANDER": 25808,
      "YADKIN": 25611,
      "CHEROKEE": 24743,
      "CURRITUCK": 24497,
      "BLADEN": 22804,
      "SCOTLAND": 21833,
      "ASHE": 20689,
      "MADISON": 17620,
      "MONTGOMERY": 17264,
      "POLK": 17212,
      "MARTIN": 16319,
      "ANSON": 15984,
      "CASWELL": 15572,
      "YANCEY": 14409,
      "HERTFORD": 13451,
      "WARREN": 13405,
      "NORTHAMPTON": 12592,
      "BERTIE": 12403,
      "AVERY": 12383,
      "MITCHELL": 11240,
      "GREENE": 10977,
      "PERQUIMANS": 10503,
      "PAMLICO": 10243,
      "CLAY": 10125,
      "CHOWAN": 10121,
      "SWAIN": 9977,
      "CAMDEN": 8532,
      "GATES": 8235,
      "ALLEGHANY": 8195,
      "WASHINGTON": 8127,
      "JONES": 6996,
      "GRAHAM": 6243,
      "HYDE": 3004,
      "TYRRELL": 2363
    }
  },
  "timestamp": "2026-03-30T10:42:29.870692"
}